control_plane_api/LICENSE
control_plane_api/README.md
control_plane_api/__init__.py
control_plane_api/__version__.py
control_plane_api/alembic.ini
control_plane_api/test_deduplication.py
control_plane_api/test_executor_deduplication_e2e.py
control_plane_api/test_job_execution_e2e.py
control_plane_api/test_real_integration.py
control_plane_api/version.py
control_plane_api/alembic/README
control_plane_api/alembic/env.py
control_plane_api/alembic/script.py.mako
control_plane_api/alembic/versions/2613c65c3dbe_initial_database_setup.py
control_plane_api/alembic/versions/2df520d4927d_merge_heads.py
control_plane_api/alembic/versions/43abf98d6a01_add_paused_status_to_executions.py
control_plane_api/alembic/versions/87d11cf0a783_add_disconnected_status_to_worker_.py
control_plane_api/alembic/versions/add_ephemeral_queue_support.py
control_plane_api/alembic/versions/add_model_type_to_llm_models.py
control_plane_api/alembic/versions/add_plan_executions_table.py
control_plane_api/alembic/versions/add_trace_span_tables.py
control_plane_api/alembic/versions/add_user_info_to_traces.py
control_plane_api/alembic/versions/adjusting_foreign_keys.py
control_plane_api/alembic/versions/b4983d976db2_initial_tables.py
control_plane_api/alembic/versions/d181a3b40e71_rename_custom_metadata_to_metadata_in_.py
control_plane_api/alembic/versions/f25de6ad895a_missing_migrations.py
control_plane_api/alembic/versions/f71305fb69b9_fix_ephemeral_queue_deletion_foreign_key.py
control_plane_api/alembic/versions/mark_local_exec_queues_as_ephemeral.py
control_plane_api/api/index.py
control_plane_api/app/__init__.py
control_plane_api/app/config.py
control_plane_api/app/database.py
control_plane_api/app/exceptions.py
control_plane_api/app/main.py
control_plane_api/app/activities/__init__.py
control_plane_api/app/activities/agent_activities.py
control_plane_api/app/activities/plan_generation_activities.py
control_plane_api/app/activities/team_activities.py
kubiya_control_plane_api-0.9.11.dist-info/licenses/LICENSE
kubiya_control_plane_api-0.9.11.dist-info/METADATA
kubiya_control_plane_api-0.9.11.dist-info/WHEEL
kubiya_control_plane_api-0.9.11.dist-info/entry_points.txt
kubiya_control_plane_api-0.9.11.dist-info/top_level.txt
kubiya_control_plane_api-0.9.11.dist-info/RECORD
