Metadata-Version: 2.4
Name: kubiya-control-plane-api
Version: 0.9.11
Summary: Agent Control Plane API - Multi-tenant AI agent orchestration and management platform
Author-email: Kubiya <support@kubiya.ai>
License: AGPL-3.0
Keywords: ai,agents,orchestration,temporal,fastapi,multi-tenant,workflow,automation
Classifier: Development Status :: 4 - Beta
Classifier: Intended Audience :: Developers
Classifier: License :: OSI Approved :: GNU Affero General Public License v3
Classifier: Programming Language :: Python :: 3
Classifier: Programming Language :: Python :: 3.10
Classifier: Programming Language :: Python :: 3.11
Classifier: Programming Language :: Python :: 3.12
Classifier: Programming Language :: Python :: 3.13
Classifier: Framework :: FastAPI
Classifier: Topic :: Software Development :: Libraries :: Application Frameworks
Classifier: Topic :: Internet :: WWW/HTTP :: HTTP Servers
Requires-Python: <4.0.0,>=3.10
License-File: LICENSE
Requires-Dist: httpx<1.0.0,>=0.26.0
Requires-Dist: pydantic<3.0.0,>=2.5.3
Requires-Dist: fastapi<1.0.0,>=0.109.0
Requires-Dist: uvicorn[standard]<1.0.0,>=0.27.0
Requires-Dist: sqlalchemy<3.0.0,>=2.0.25
Requires-Dist: psycopg2-binary<3.0.0,>=2.9.9
Requires-Dist: pydantic-settings<3.0.0,>=2.1.0
Requires-Dist: alembic<2.0.0,>=1.13.1
Requires-Dist: supabase<3.0.0,>=2.3.0
Requires-Dist: temporalio<2.0.0,>=1.5.0
Requires-Dist: python-multipart<1.0.0,>=0.0.6
Requires-Dist: python-jose[cryptography]<4.0.0,>=3.3.0
Requires-Dist: PyJWT<3.0.0,>=2.8.0
Requires-Dist: passlib[bcrypt]<2.0.0,>=1.7.4
Requires-Dist: mangum<1.0.0,>=0.17.0
Requires-Dist: structlog<25.0.0,>=24.1.0
Requires-Dist: croniter<3.0.0,>=2.0.0
Requires-Dist: litellm<2.0.0,>=1.30.0
Requires-Dist: agno<3.0.0,>=2.3.12
Requires-Dist: mcp<2.0.0,>=1.0.0
Requires-Dist: redis<6.0.0,>=5.0.0
Requires-Dist: kubiya-sdk<3.0.0,>=2.0.3
Requires-Dist: websockets<16.0.0,>=15.0
Requires-Dist: python-dotenv<2.0.0,>=1.0.0
Requires-Dist: anthropic<1.0.0,>=0.39.0
Requires-Dist: claude-agent-sdk>=0.1.6
Requires-Dist: opentelemetry-api<2.0.0,>=1.20.0
Requires-Dist: opentelemetry-sdk<2.0.0,>=1.20.0
Requires-Dist: opentelemetry-instrumentation-fastapi<1.0.0,>=0.41b0
Requires-Dist: opentelemetry-instrumentation-sqlalchemy<1.0.0,>=0.41b0
Requires-Dist: opentelemetry-instrumentation-redis<1.0.0,>=0.41b0
Requires-Dist: opentelemetry-instrumentation-httpx<1.0.0,>=0.41b0
Requires-Dist: opentelemetry-exporter-otlp-proto-grpc<2.0.0,>=1.20.0
Requires-Dist: opentelemetry-exporter-otlp-proto-http<2.0.0,>=1.20.0
Provides-Extra: worker
Requires-Dist: temporalio<2.0.0,>=1.5.0; extra == "worker"
Requires-Dist: structlog<25.0.0,>=24.1.0; extra == "worker"
Requires-Dist: agno<3.0.0,>=2.3.12; extra == "worker"
Requires-Dist: litellm<2.0.0,>=1.30.0; extra == "worker"
Requires-Dist: psutil<6.0.0,>=5.9.0; extra == "worker"
Requires-Dist: docker<8.0.0,>=7.0.0; extra == "worker"
Requires-Dist: redis<6.0.0,>=5.0.0; extra == "worker"
Requires-Dist: mcp<2.0.0,>=1.0.0; extra == "worker"
Requires-Dist: nest-asyncio<2.0.0,>=1.5.0; extra == "worker"
Requires-Dist: claude-agent-sdk<1.0.0,>=0.1.0; extra == "worker"
Provides-Extra: api
Requires-Dist: fastapi<1.0.0,>=0.109.0; extra == "api"
Requires-Dist: uvicorn[standard]<1.0.0,>=0.27.0; extra == "api"
Requires-Dist: sqlalchemy<3.0.0,>=2.0.25; extra == "api"
Requires-Dist: psycopg2-binary<3.0.0,>=2.9.9; extra == "api"
Requires-Dist: pydantic-settings<3.0.0,>=2.1.0; extra == "api"
Requires-Dist: alembic<2.0.0,>=1.13.1; extra == "api"
Requires-Dist: supabase<3.0.0,>=2.3.0; extra == "api"
Requires-Dist: temporalio<2.0.0,>=1.5.0; extra == "api"
Requires-Dist: python-multipart<1.0.0,>=0.0.6; extra == "api"
Requires-Dist: python-jose[cryptography]<4.0.0,>=3.3.0; extra == "api"
Requires-Dist: PyJWT<3.0.0,>=2.8.0; extra == "api"
Requires-Dist: passlib[bcrypt]<2.0.0,>=1.7.4; extra == "api"
Requires-Dist: mangum<1.0.0,>=0.17.0; extra == "api"
Requires-Dist: structlog<25.0.0,>=24.1.0; extra == "api"
Requires-Dist: croniter<3.0.0,>=2.0.0; extra == "api"
Requires-Dist: kubiya-sdk<3.0.0,>=2.0.3; extra == "api"
Provides-Extra: dev
Requires-Dist: pytest<9.0.0,>=7.4.0; extra == "dev"
Requires-Dist: pytest-asyncio<1.0.0,>=0.21.0; extra == "dev"
Requires-Dist: pytest-cov<6.0.0,>=4.1.0; extra == "dev"
Requires-Dist: pytest-mock<4.0.0,>=3.11.0; extra == "dev"
Requires-Dist: pytest-xdist<4.0.0,>=3.5.0; extra == "dev"
Requires-Dist: fakeredis<3.0.0,>=2.20.0; extra == "dev"
Requires-Dist: respx<1.0.0,>=0.20.0; extra == "dev"
Requires-Dist: black<25.0.0,>=23.0.0; extra == "dev"
Requires-Dist: ruff<1.0.0,>=0.1.0; extra == "dev"
Requires-Dist: mypy<2.0.0,>=1.0.0; extra == "dev"
Provides-Extra: test
Requires-Dist: pytest<9.0.0,>=7.4.0; extra == "test"
Requires-Dist: pytest-asyncio<1.0.0,>=0.21.0; extra == "test"
Requires-Dist: pytest-cov<6.0.0,>=4.1.0; extra == "test"
Requires-Dist: pytest-mock<4.0.0,>=3.11.0; extra == "test"
Requires-Dist: pytest-xdist<4.0.0,>=3.5.0; extra == "test"
Requires-Dist: fakeredis<3.0.0,>=2.20.0; extra == "test"
Requires-Dist: respx<1.0.0,>=0.20.0; extra == "test"
Provides-Extra: yaml
Requires-Dist: PyYAML<7.0.0,>=6.0.1; extra == "yaml"
Provides-Extra: nats
Requires-Dist: nats-py<3.0.0,>=2.6.0; extra == "nats"
Requires-Dist: nkeys<1.0.0,>=0.1.0; extra == "nats"
Provides-Extra: event-bus
Requires-Dist: kubiya-control-plane-api[nats,yaml]; extra == "event-bus"
Provides-Extra: all
Requires-Dist: kubiya-control-plane-api[api,dev,event-bus,test,worker]; extra == "all"
Dynamic: license-file
